botcity_maestro_client-1.0.1.dist-info/licenses/LICENSE
maestro_client/__init__.py
maestro_client/maestro_client.py
maestro_client/helpers/__init__.py
maestro_client/helpers/data_models.py
maestro_client/helpers/exceptions.py
maestro_client/helpers/response_utils.py
botcity_maestro_client-1.0.1.dist-info/METADATA
botcity_maestro_client-1.0.1.dist-info/WHEEL
botcity_maestro_client-1.0.1.dist-info/top_level.txt
botcity_maestro_client-1.0.1.dist-info/RECORD
