Metadata-Version: 2.4
Name: botcity-maestro-client
Version: 1.0.1
Summary: A lightweight Python SDK for interacting with the BotCity Maestro API v2.
Author-email: Ausier <ausierneto@gmail.com>
License: MIT
Project-URL: Homepage, https://github.com/AusierNeto/maestro-sdk
Project-URL: Documentation, https://github.com/AusierNeto/maestro-sdk
Project-URL: Source, https://github.com/AusierNeto/maestro-sdk
Project-URL: Issues, https://github.com/AusierNeto/maestro-sdk/issues
Keywords: botcity,maestro,automation,sdk,api,client
Classifier: Programming Language :: Python :: 3
Classifier: License :: OSI Approved :: MIT License
Classifier: Operating System :: OS Independent
Classifier: Intended Audience :: Developers
Classifier: Topic :: Software Development :: Libraries :: Python Modules
Requires-Python: >=3.8
License-File: LICENSE
Requires-Dist: requests>=2.32.5
Dynamic: license-file
